tinderbox/__init__.py
tinderbox/__version__.py
tinderbox/smoke.py
tinderbox/tinder.py
tinderbox-0.0.6.dist-info/LICENSE
tinderbox-0.0.6.dist-info/METADATA
tinderbox-0.0.6.dist-info/WHEEL
tinderbox-0.0.6.dist-info/top_level.txt
tinderbox-0.0.6.dist-info/RECORD
